textzle/__init__.py
textzle/main.py
textzle-0.1.1.dist-info/LICENSE
textzle-0.1.1.dist-info/METADATA
textzle-0.1.1.dist-info/WHEEL
textzle-0.1.1.dist-info/RECORD
