Metadata-Version: 2.3
Name: textzle
Version: 0.1.1
Summary: This is the base engine for Textzle, a text adventure game.
License: MIT
Author: splot.dev
Requires-Python: >=3.10
Classifier: License :: OSI Approved :: MIT License
Classifier: Programming Language :: Python :: 3
Classifier: Programming Language :: Python :: 3.10
Classifier: Programming Language :: Python :: 3.11
Classifier: Programming Language :: Python :: 3.12
Classifier: Programming Language :: Python :: 3.13
